{
  "$schema": "http://json-schema.org/draft-07/schema#",
  "$id": "http://example.com/INCLUDE.Study.manifest",
  "title": "INCLUDE.Study.manifest",
  "type": "object",
  "properties": {
    "Study Name": {
      "not": {
        "type": "null"
      },
      "minLength": 1
    },
    "Study Code": {
      "enum": [
        "DS-DETERMINED",
        "TRC-DS",
        "ECODS",
        "AECOM-DS",
        "BrainPower",
        "DS-PALS",
        "ExCEEDS",
        "ADS",
        "DS-HSAT",
        "DS-Nexus",
        "DS-Sleep",
        "X01-Hakon",
        "DS-COG-AML",
        "DS-ISP",
        "HTP",
        "DS-PCGC",
        "X01-deSmith",
        "DS-Brain",
        "BRI-DSR",
        "DSC",
        "ABC-DS",
        "CHARGE-DS",
        "DS-COG-ALL",
        "DS360-CHD"
      ]
    },
    "dbGap": {},
    "Program": {
      "enum": [
        "INCLUDE",
        "KF"
      ]
    },
    "Participant ID": {
      "not": {
        "type": "null"
      },
      "minLength": 1
    }
  },
  "required": [
    "Study Name",
    "Study Code",
    "Program",
    "Participant ID"
  ]
}